README.txt
buildout.cfg
setup.py
src/zc/__init__.py
src/zc.zodbactivitylog.egg-info/PKG-INFO
src/zc.zodbactivitylog.egg-info/SOURCES.txt
src/zc.zodbactivitylog.egg-info/dependency_links.txt
src/zc.zodbactivitylog.egg-info/entry_points.txt
src/zc.zodbactivitylog.egg-info/namespace_packages.txt
src/zc.zodbactivitylog.egg-info/not-zip-safe
src/zc.zodbactivitylog.egg-info/requires.txt
src/zc.zodbactivitylog.egg-info/top_level.txt
src/zc/zodbactivitylog/__init__.py
src/zc/zodbactivitylog/configure.zcml
src/zc/zodbactivitylog/report.py
src/zc/zodbactivitylog/zope3.py
