Metadata-Version: 1.0
Name: zc.zodbactivitylog
Version: 0.1.1
Summary: ZODB Activity Monitor that just logs
Home-page: UNKNOWN
Author: Jim Fulton
Author-email: jim@zope.com
License: ZPL 2.1
Platform: UNKNOWN
